{
    "reason": "Success",
    "result": {
        "data": [
            {
                "content": "设计师你过来，我保证不打你！",
                "hashId": "0F0024F3118F4BA6E3EA87C9FC0D00B4",
                "unixtime": "1468229608",
                "updatetime": "2016-07-11 17:33:28",
                "url": "http://juheimg.oss-cn-hangzhou.aliyuncs.com/joke/201607/11/0F0024F3118F4BA6E3EA87C9FC0D00B4.gif"
            },
            {
                "content": "上万家长联名要求葛优拍一张“端坐照”",
                "hashId": "AF9888EE06BEEF1B9BBECD8B9269851A",
                "unixtime": "1468229607",
                "updatetime": "2016-07-11 17:33:27",
                "url": "http://juheimg.oss-cn-hangzhou.aliyuncs.com/joke/201607/11/AF9888EE06BEEF1B9BBECD8B9269851A.jpg"
            },
            {
                "content": "看把宝宝急得，都有小情绪了",
                "hashId": "EEA4B9485B8AEFCED3BF8ECD87841A0A",
                "unixtime": "1468229607",
                "updatetime": "2016-07-11 17:33:27",
                "url": "http://juheimg.oss-cn-hangzhou.aliyuncs.com/joke/201607/11/EEA4B9485B8AEFCED3BF8ECD87841A0A.gif"
            },
            {
                "content": "主人提前回家抓拍到了这一幕……主人：我不在家时你们都在干什么？？？",
                "hashId": "E8DB264A89A3DB66CD600CE6C95958B2",
                "unixtime": "1468229607",
                "updatetime": "2016-07-11 17:33:27",
                "url": "http://juheimg.oss-cn-hangzhou.aliyuncs.com/joke/201607/11/E8DB264A89A3DB66CD600CE6C95958B2.jpg"
            },
            {
                "content": "屁股还是胸？完全看不出来啊",
                "hashId": "C0C3C33D46B38110C5A255884FA3C787",
                "unixtime": "1468229607",
                "updatetime": "2016-07-11 17:33:27",
                "url": "http://juheimg.oss-cn-hangzhou.aliyuncs.com/joke/201607/11/C0C3C33D46B38110C5A255884FA3C787.jpg"
            },
            {
                "content": "不平易近人，要凸凹有致！",
                "hashId": "B2C8E5682E0901C423B97943AE816E2C",
                "unixtime": "1468229607",
                "updatetime": "2016-07-11 17:33:27",
                "url": "http://juheimg.oss-cn-hangzhou.aliyuncs.com/joke/201607/11/B2C8E5682E0901C423B97943AE816E2C.jpg"
            },
            {
                "content": "男人都换老婆了，女人你啥时候换手机啊",
                "hashId": "592028A8BE917E6875F19BA5C39F2AA1",
                "unixtime": "1468229607",
                "updatetime": "2016-07-11 17:33:27",
                "url": "http://juheimg.oss-cn-hangzhou.aliyuncs.com/joke/201607/11/592028A8BE917E6875F19BA5C39F2AA1.jpg"
            },
            {
                "content": "火车上看见的消魂睡姿",
                "hashId": "5DBA902459C9D15CEE7268545750B2F1",
                "unixtime": "1468229607",
                "updatetime": "2016-07-11 17:33:27",
                "url": "http://juheimg.oss-cn-hangzhou.aliyuncs.com/joke/201607/11/5DBA902459C9D15CEE7268545750B2F1.jpg"
            },
            {
                "content": "最美的青春",
                "hashId": "8CC6860B9D4E34D136A6EE340D562554",
                "unixtime": "1468229607",
                "updatetime": "2016-07-11 17:33:27",
                "url": "http://juheimg.oss-cn-hangzhou.aliyuncs.com/joke/201607/11/8CC6860B9D4E34D136A6EE340D562554.jpg"
            },
            {
                "content": "这才是真正的人们警察",
                "hashId": "E5A9DF04A381978BB031770DA2EDD42E",
                "unixtime": "1468229607",
                "updatetime": "2016-07-11 17:33:27",
                "url": "http://juheimg.oss-cn-hangzhou.aliyuncs.com/joke/201607/11/E5A9DF04A381978BB031770DA2EDD42E.jpg"
            },
            {
                "content": "老板，你故意的吧！",
                "hashId": "93CEDB9BECE0D8B267A98F51069B3247",
                "unixtime": "1468229607",
                "updatetime": "2016-07-11 17:33:27",
                "url": "http://juheimg.oss-cn-hangzhou.aliyuncs.com/joke/201607/11/93CEDB9BECE0D8B267A98F51069B3247.jpg"
            },
            {
                "content": "老板，你故意的吧！",
                "hashId": "89ABC2F655336997A57A22C7436DE5EE",
                "unixtime": "1468229607",
                "updatetime": "2016-07-11 17:33:27",
                "url": "http://juheimg.oss-cn-hangzhou.aliyuncs.com/joke/201607/11/89ABC2F655336997A57A22C7436DE5EE.jpg"
            },
            {
                "content": "夏日的风景，接地气，比较凉快？",
                "hashId": "F2CBB37B7FADE76C0B68C839BD303BB8",
                "unixtime": "1468229607",
                "updatetime": "2016-07-11 17:33:27",
                "url": "http://juheimg.oss-cn-hangzhou.aliyuncs.com/joke/201607/11/F2CBB37B7FADE76C0B68C839BD303BB8.jpg"
            },
            {
                "content": "爸爸的爱",
                "hashId": "6EDE1BA22B23CADDC20CAD37CA16D2C3",
                "unixtime": "1468229607",
                "updatetime": "2016-07-11 17:33:27",
                "url": "http://juheimg.oss-cn-hangzhou.aliyuncs.com/joke/201607/11/6EDE1BA22B23CADDC20CAD37CA16D2C3.jpg"
            },
            {
                "content": "就是这么帅！帅爆的gif图片",
                "hashId": "953A6417E748EC07656E840041D3E11B",
                "unixtime": "1468229607",
                "updatetime": "2016-07-11 17:33:27",
                "url": "http://juheimg.oss-cn-hangzhou.aliyuncs.com/joke/201607/11/953A6417E748EC07656E840041D3E11B.gif"
            },
            {
                "content": "我和我最后的倔强。。。",
                "hashId": "E21156C522572A4CC0CF677897C816AA",
                "unixtime": "1468056794",
                "updatetime": "2016-07-09 17:33:14",
                "url": "http://juheimg.oss-cn-hangzhou.aliyuncs.com/joke/201607/09/E21156C522572A4CC0CF677897C816AA.gif"
            },
            {
                "content": "为什么女生喜欢看小电影？没你想得那么肤浅！ 并不是为你看的，她们只是想自己舒服",
                "hashId": "AA2B06B5750B8BE4F77B2D2BB4B13AB0",
                "unixtime": "1468056794",
                "updatetime": "2016-07-09 17:33:14",
                "url": "http://juheimg.oss-cn-hangzhou.aliyuncs.com/joke/201607/09/AA2B06B5750B8BE4F77B2D2BB4B13AB0.gif"
            },
            {
                "content": "冲锋衣",
                "hashId": "28EE9644D57FA7B31AD0EE52691CEFCE",
                "unixtime": "1468056794",
                "updatetime": "2016-07-09 17:33:14",
                "url": "http://juheimg.oss-cn-hangzhou.aliyuncs.com/joke/201607/09/28EE9644D57FA7B31AD0EE52691CEFCE.png"
            },
            {
                "content": "关于英国脱欧，暴走这个视频做的太魔性了！",
                "hashId": "C0B2BFCFFC800DC51B10DA12138A791A",
                "unixtime": "1468056794",
                "updatetime": "2016-07-09 17:33:14",
                "url": "http://juheimg.oss-cn-hangzhou.aliyuncs.com/joke/201607/09/C0B2BFCFFC800DC51B10DA12138A791A.png"
            },
            {
                "content": "歪果仁的中文考试",
                "hashId": "9BC3CDD48DBE98851AEE3A52008D0075",
                "unixtime": "1468056794",
                "updatetime": "2016-07-09 17:33:14",
                "url": "http://juheimg.oss-cn-hangzhou.aliyuncs.com/joke/201607/09/9BC3CDD48DBE98851AEE3A52008D0075.png"
            }
        ]
    },
    "error_code": "0"
}