{
    "reason": "Success",
    "result": {
        "data": [
            {
                "content": "太生动了，今儿个算是知道怎么辨别包包真假了",
                "hashId": "FFD98AAEEEC461878AA2A6EB71677B24",
                "unixtime": "1483949118",
                "updatetime": "2017-01-09 16:05:18",
                "url": "http://juheimg.oss-cn-hangzhou.aliyuncs.com/joke/201701/09/FFD98AAEEEC461878AA2A6EB71677B24.jpg"
            },
            {
                "content": "金星问一个男嘉宾妈妈，对儿媳妇有什么要求，这妇女说手脚冰凉的不能要，因为她是一个高级营养师，知道手脚冰凉的女的宫寒。你宫不寒，你的子宫冬暖夏凉",
                "hashId": "5B69CF3BEA04B76844440C2C3F2E298B",
                "unixtime": "1483949118",
                "updatetime": "2017-01-09 16:05:18",
                "url": "http://juheimg.oss-cn-hangzhou.aliyuncs.com/joke/201701/09/5B69CF3BEA04B76844440C2C3F2E298B.jpg"
            },
            {
                "content": "论为什么遇到喜欢的人却不会主动出击",
                "hashId": "C0F267D628D33813F7786BC902B0C562",
                "unixtime": "1483949118",
                "updatetime": "2017-01-09 16:05:18",
                "url": "http://juheimg.oss-cn-hangzhou.aliyuncs.com/joke/201701/09/C0F267D628D33813F7786BC902B0C562.jpg"
            },
            {
                "content": "没点体力还真扛不住这样热情洋溢的迎接：宝宝等你很久了，要抱抱，举高高.....",
                "hashId": "10833DA67BE5C1DCE34A85BDDAC3C200",
                "unixtime": "1483949118",
                "updatetime": "2017-01-09 16:05:18",
                "url": "http://juheimg.oss-cn-hangzhou.aliyuncs.com/joke/201701/09/10833DA67BE5C1DCE34A85BDDAC3C200.gif"
            },
            {
                "content": "八达岭被咬女子遭保安大骂：老虎没咬死你真可惜",
                "hashId": "B48ECAEFF9205D53F6D026A9593CD997",
                "unixtime": "1483949118",
                "updatetime": "2017-01-09 16:05:18",
                "url": "http://juheimg.oss-cn-hangzhou.aliyuncs.com/joke/201701/09/B48ECAEFF9205D53F6D026A9593CD997.jpg"
            },
            {
                "content": "日本学者：今年流行色不选红色将有世纪大灾难",
                "hashId": "5D6D15AFFC1173685882B286DD7DC5CB",
                "unixtime": "1483949118",
                "updatetime": "2017-01-09 16:05:18",
                "url": "http://juheimg.oss-cn-hangzhou.aliyuncs.com/joke/201701/09/5D6D15AFFC1173685882B286DD7DC5CB.jpg"
            },
            {
                "content": "你最讨厌对方回复什么？",
                "hashId": "C67A2FE6722A5B4EE81180E1F2C813F2",
                "unixtime": "1483949118",
                "updatetime": "2017-01-09 16:05:18",
                "url": "http://juheimg.oss-cn-hangzhou.aliyuncs.com/joke/201701/09/C67A2FE6722A5B4EE81180E1F2C813F2.jpg"
            },
            {
                "content": "单纯的骗子",
                "hashId": "59B778CFEA89EEAE6F2C758BEECD1DC5",
                "unixtime": "1483934742",
                "updatetime": "2017-01-09 12:05:42",
                "url": "http://juheimg.oss-cn-hangzhou.aliyuncs.com/joke/201701/09/59B778CFEA89EEAE6F2C758BEECD1DC5.jpg"
            },
            {
                "content": "单纯的骗子",
                "hashId": "EE34C1A682B1D8EB56601DD829340A87",
                "unixtime": "1483934742",
                "updatetime": "2017-01-09 12:05:42",
                "url": "http://juheimg.oss-cn-hangzhou.aliyuncs.com/joke/201701/09/EE34C1A682B1D8EB56601DD829340A87.gif"
            },
            {
                "content": "没毛病",
                "hashId": "61E06F3CA2BA6BBE81723B15127C3F82",
                "unixtime": "1483934742",
                "updatetime": "2017-01-09 12:05:42",
                "url": "http://juheimg.oss-cn-hangzhou.aliyuncs.com/joke/201701/09/61E06F3CA2BA6BBE81723B15127C3F82.jpg"
            },
            {
                "content": "这么优秀的传统.....居然丢了.....",
                "hashId": "7901AD06120FBE04B22CF7C196440D01",
                "unixtime": "1483934742",
                "updatetime": "2017-01-09 12:05:42",
                "url": "http://juheimg.oss-cn-hangzhou.aliyuncs.com/joke/201701/09/7901AD06120FBE04B22CF7C196440D01.jpg"
            },
            {
                "content": "篮球宝贝也兴cosplay？！江苏肯帝亚篮球宝贝星际战士形象",
                "hashId": "AE6BA7356B3F5B65321D557D35DB06B1",
                "unixtime": "1483934742",
                "updatetime": "2017-01-09 12:05:42",
                "url": "http://juheimg.oss-cn-hangzhou.aliyuncs.com/joke/201701/09/AE6BA7356B3F5B65321D557D35DB06B1.jpg"
            },
            {
                "content": "冬天最冷的时候到了，是养身的时候了",
                "hashId": "F6DB382398A39949FE45AB8A4796E0AD",
                "unixtime": "1483934742",
                "updatetime": "2017-01-09 12:05:42",
                "url": "http://juheimg.oss-cn-hangzhou.aliyuncs.com/joke/201701/09/F6DB382398A39949FE45AB8A4796E0AD.jpg"
            },
            {
                "content": "长度和硬度都可以，就是不知道持久度怎么样",
                "hashId": "07A9A470B0064B7E2ACD590037331C87",
                "unixtime": "1483934742",
                "updatetime": "2017-01-09 12:05:42",
                "url": "http://juheimg.oss-cn-hangzhou.aliyuncs.com/joke/201701/09/07A9A470B0064B7E2ACD590037331C87.jpg"
            },
            {
                "content": "幼儿园老师是个危险职业",
                "hashId": "EB653062653E02CD77C2A1C7BB47C515",
                "unixtime": "1483783508",
                "updatetime": "2017-01-07 18:05:08",
                "url": "http://juheimg.oss-cn-hangzhou.aliyuncs.com/joke/201701/07/EB653062653E02CD77C2A1C7BB47C515.gif"
            },
            {
                "content": "跨年夜，南京一小区发生离奇坠楼有邻居称，坠亡男子当时在女同事家，对方丈夫突然回家，顺着床单下楼不慎失手",
                "hashId": "4B95EC17CDCD8536CCC9D360374B154D",
                "unixtime": "1483783508",
                "updatetime": "2017-01-07 18:05:08",
                "url": "http://juheimg.oss-cn-hangzhou.aliyuncs.com/joke/201701/07/4B95EC17CDCD8536CCC9D360374B154D.jpg"
            },
            {
                "content": "“学习不好长大了干嘛？”“结婚”",
                "hashId": "015ED199FE29BACBCEA0B96BF75A29AC",
                "unixtime": "1483783508",
                "updatetime": "2017-01-07 18:05:08",
                "url": "http://juheimg.oss-cn-hangzhou.aliyuncs.com/joke/201701/07/015ED199FE29BACBCEA0B96BF75A29AC.jpg"
            },
            {
                "content": "《中国建筑结合环境造出人间仙境 令世界赞叹不已称巧夺天工》",
                "hashId": "D77B79D97238FF3A8273648264473BD8",
                "unixtime": "1483783508",
                "updatetime": "2017-01-07 18:05:08",
                "url": "http://juheimg.oss-cn-hangzhou.aliyuncs.com/joke/201701/07/D77B79D97238FF3A8273648264473BD8.jpg"
            },
            {
                "content": "分享一个不错的新技能～",
                "hashId": "C4044A8EDDD85AC140E2820755BD2961",
                "unixtime": "1483783508",
                "updatetime": "2017-01-07 18:05:08",
                "url": "http://juheimg.oss-cn-hangzhou.aliyuncs.com/joke/201701/07/C4044A8EDDD85AC140E2820755BD2961.jpg"
            },
            {
                "content": "看我嘴型，去你妈了逼！",
                "hashId": "439BF91732D9FB14B06D89712FDDDC1A",
                "unixtime": "1483783508",
                "updatetime": "2017-01-07 18:05:08",
                "url": "http://juheimg.oss-cn-hangzhou.aliyuncs.com/joke/201701/07/439BF91732D9FB14B06D89712FDDDC1A.jpg"
            }
        ]
    },
    "error_code": "0"
}