{
    "reason": "Success",
    "result": {
        "data": [
            {
                "content": "圣诞没啥意思。自己吃泡面吧",
                "hashId": "CCAB748CE7E57D05F1692C8067B797C8",
                "unixtime": "1482552306",
                "updatetime": "2016-12-24 12:05:06",
                "url": "http://juheimg.oss-cn-hangzhou.aliyuncs.com/joke/201612/24/CCAB748CE7E57D05F1692C8067B797C8.jpg"
            },
            {
                "content": "我的三观成了渣",
                "hashId": "CB0A867EE27A65CC88FBEB7E5B369835",
                "unixtime": "1482552306",
                "updatetime": "2016-12-24 12:05:06",
                "url": "http://juheimg.oss-cn-hangzhou.aliyuncs.com/joke/201612/24/CB0A867EE27A65CC88FBEB7E5B369835.png"
            },
            {
                "content": "我与网红之间差一个P图师",
                "hashId": "4A088BD9D08C702A5556ECB6D3D0155B",
                "unixtime": "1482552306",
                "updatetime": "2016-12-24 12:05:06",
                "url": "http://juheimg.oss-cn-hangzhou.aliyuncs.com/joke/201612/24/4A088BD9D08C702A5556ECB6D3D0155B.png"
            },
            {
                "content": "买家秀记得露脸哦",
                "hashId": "B9134345783148C05816982B8D16BEB2",
                "unixtime": "1482552306",
                "updatetime": "2016-12-24 12:05:06",
                "url": "http://juheimg.oss-cn-hangzhou.aliyuncs.com/joke/201612/24/B9134345783148C05816982B8D16BEB2.jpg"
            },
            {
                "content": "年底了，我要八一八我的奇葩老板",
                "hashId": "8ED3055C6BBF356555D88322BD50E2A3",
                "unixtime": "1482552306",
                "updatetime": "2016-12-24 12:05:06",
                "url": "http://juheimg.oss-cn-hangzhou.aliyuncs.com/joke/201612/24/8ED3055C6BBF356555D88322BD50E2A3.png"
            },
            {
                "content": "还真是随便啊",
                "hashId": "C3A6D44D3D43F5B89E46442147491E88",
                "unixtime": "1482552306",
                "updatetime": "2016-12-24 12:05:06",
                "url": "http://juheimg.oss-cn-hangzhou.aliyuncs.com/joke/201612/24/C3A6D44D3D43F5B89E46442147491E88.jpg"
            },
            {
                "content": "绝对是正确的科学发展观！",
                "hashId": "416367892ACF2FD1E6780A88A3FC363E",
                "unixtime": "1482552306",
                "updatetime": "2016-12-24 12:05:06",
                "url": "http://juheimg.oss-cn-hangzhou.aliyuncs.com/joke/201612/24/416367892ACF2FD1E6780A88A3FC363E.jpg"
            },
            {
                "content": "妹子打算COS寒冰？",
                "hashId": "359BB05917CF2E506EE8A9C32142D04F",
                "unixtime": "1482552306",
                "updatetime": "2016-12-24 12:05:06",
                "url": "http://juheimg.oss-cn-hangzhou.aliyuncs.com/joke/201612/24/359BB05917CF2E506EE8A9C32142D04F.gif"
            },
            {
                "content": "下面吹曲子...这个优胜也算是众望所归了",
                "hashId": "FD677A606E78F887D556422BEF4A8F49",
                "unixtime": "1482552306",
                "updatetime": "2016-12-24 12:05:06",
                "url": "http://juheimg.oss-cn-hangzhou.aliyuncs.com/joke/201612/24/FD677A606E78F887D556422BEF4A8F49.gif"
            },
            {
                "content": "美杜莎之战",
                "hashId": "89CA4B061597BDE3A641C28250880EDA",
                "unixtime": "1482552306",
                "updatetime": "2016-12-24 12:05:06",
                "url": "http://juheimg.oss-cn-hangzhou.aliyuncs.com/joke/201612/24/89CA4B061597BDE3A641C28250880EDA.gif"
            },
            {
                "content": "每次看到同学在吃东西的你",
                "hashId": "958A5BFA85E2C3F5A66E0E32AA558193",
                "unixtime": "1482487517",
                "updatetime": "2016-12-23 18:05:17",
                "url": "http://juheimg.oss-cn-hangzhou.aliyuncs.com/joke/201612/23/958A5BFA85E2C3F5A66E0E32AA558193.jpg"
            },
            {
                "content": "这姑娘真调皮",
                "hashId": "F306F2BDC85AADA34B76CC9E647A9AFA",
                "unixtime": "1482487517",
                "updatetime": "2016-12-23 18:05:17",
                "url": "http://juheimg.oss-cn-hangzhou.aliyuncs.com/joke/201612/23/F306F2BDC85AADA34B76CC9E647A9AFA.gif"
            },
            {
                "content": "现在已经开始流行丝震了",
                "hashId": "A2578AC44E0F4AB94B5970AC8C123B62",
                "unixtime": "1482473107",
                "updatetime": "2016-12-23 14:05:07",
                "url": "http://juheimg.oss-cn-hangzhou.aliyuncs.com/joke/201612/23/A2578AC44E0F4AB94B5970AC8C123B62.gif"
            },
            {
                "content": "请推理00后",
                "hashId": "0606EE0FA93D32161CFCC41B5486F528",
                "unixtime": "1482473107",
                "updatetime": "2016-12-23 14:05:07",
                "url": "http://juheimg.oss-cn-hangzhou.aliyuncs.com/joke/201612/23/0606EE0FA93D32161CFCC41B5486F528.jpg"
            },
            {
                "content": "大写的心疼",
                "hashId": "95240ED078DC8A4C1FF6658128592970",
                "unixtime": "1482473107",
                "updatetime": "2016-12-23 14:05:07",
                "url": "http://juheimg.oss-cn-hangzhou.aliyuncs.com/joke/201612/23/95240ED078DC8A4C1FF6658128592970.jpg"
            },
            {
                "content": "水好多",
                "hashId": "20A9D298CD35906279B7C5F0CDAE8959",
                "unixtime": "1482473107",
                "updatetime": "2016-12-23 14:05:07",
                "url": "http://juheimg.oss-cn-hangzhou.aliyuncs.com/joke/201612/23/20A9D298CD35906279B7C5F0CDAE8959.jpg"
            },
            {
                "content": "一起组个乐队，藏蓝瓜子？？？？？",
                "hashId": "4C203692A4FC2B430A24D504DCF7FD00",
                "unixtime": "1482473107",
                "updatetime": "2016-12-23 14:05:07",
                "url": "http://juheimg.oss-cn-hangzhou.aliyuncs.com/joke/201612/23/4C203692A4FC2B430A24D504DCF7FD00.jpg"
            },
            {
                "content": "最喜欢哪个",
                "hashId": "DB5D264A870780C91BDF0876136E8F06",
                "unixtime": "1482473107",
                "updatetime": "2016-12-23 14:05:07",
                "url": "http://juheimg.oss-cn-hangzhou.aliyuncs.com/joke/201612/23/DB5D264A870780C91BDF0876136E8F06.gif"
            },
            {
                "content": "这衣服好看",
                "hashId": "9012A611D9889B053528F9E7374E05FE",
                "unixtime": "1482473107",
                "updatetime": "2016-12-23 14:05:07",
                "url": "http://juheimg.oss-cn-hangzhou.aliyuncs.com/joke/201612/23/9012A611D9889B053528F9E7374E05FE.gif"
            },
            {
                "content": "室友可能把持不住",
                "hashId": "118FA5EFD5A5ECC80DB62E7959384727",
                "unixtime": "1482473107",
                "updatetime": "2016-12-23 14:05:07",
                "url": "http://juheimg.oss-cn-hangzhou.aliyuncs.com/joke/201612/23/118FA5EFD5A5ECC80DB62E7959384727.jpg"
            }
        ]
    },
    "error_code": "0"
}