{
    "reason": "Success",
    "result": {
        "data": [
            {
                "content": "日本的职业鞭者林丽奈……看完之后，你们有没有觉得哪里有点疼",
                "hashId": "46B3AA475951827B78DE98840DB8E7D6",
                "unixtime": "1473759314",
                "updatetime": "2016-09-13 17:35:14",
                "url": "http://juheimg.oss-cn-hangzhou.aliyuncs.com/joke/201609/13/46B3AA475951827B78DE98840DB8E7D6.gif"
            },
            {
                "content": "能不能好好的游泳",
                "hashId": "953EFB99C3C4D6E067C8DC9AF0728FB9",
                "unixtime": "1473757506",
                "updatetime": "2016-09-13 17:05:06",
                "url": "http://juheimg.oss-cn-hangzhou.aliyuncs.com/joke/201609/13/953EFB99C3C4D6E067C8DC9AF0728FB9.gif"
            },
            {
                "content": "一股清流",
                "hashId": "5ED7FF678B1269B8ED23B821F764F1DB",
                "unixtime": "1473757506",
                "updatetime": "2016-09-13 17:05:06",
                "url": "http://juheimg.oss-cn-hangzhou.aliyuncs.com/joke/201609/13/5ED7FF678B1269B8ED23B821F764F1DB.jpg"
            },
            {
                "content": "大伯臀部大面积烧伤 疑是小米手机起火",
                "hashId": "4A83D2C58A471288C994AC243C15A874",
                "unixtime": "1473757506",
                "updatetime": "2016-09-13 17:05:06",
                "url": "http://juheimg.oss-cn-hangzhou.aliyuncs.com/joke/201609/13/4A83D2C58A471288C994AC243C15A874.png"
            },
            {
                "content": "一网友回到家看到这一幕吓得差点大哭，然后把熊孩子胖揍了一顿",
                "hashId": "B0A14143E7CF5570E53D6E25F542FE6F",
                "unixtime": "1473757506",
                "updatetime": "2016-09-13 17:05:06",
                "url": "http://juheimg.oss-cn-hangzhou.aliyuncs.com/joke/201609/13/B0A14143E7CF5570E53D6E25F542FE6F.jpg"
            },
            {
                "content": "易到用车终于放出了杀手锏，滴滴你颤抖吧！",
                "hashId": "8AA36B936AC53DAFB7ADC2EF8DEC11C9",
                "unixtime": "1473757506",
                "updatetime": "2016-09-13 17:05:06",
                "url": "http://juheimg.oss-cn-hangzhou.aliyuncs.com/joke/201609/13/8AA36B936AC53DAFB7ADC2EF8DEC11C9.png"
            },
            {
                "content": "接个吻都不能好好的",
                "hashId": "2AB85EFA7933352A5E557D21289B8EE3",
                "unixtime": "1473755706",
                "updatetime": "2016-09-13 16:35:06",
                "url": "http://juheimg.oss-cn-hangzhou.aliyuncs.com/joke/201609/13/2AB85EFA7933352A5E557D21289B8EE3.gif"
            },
            {
                "content": "工作前VS工作后，这样的对比简直了",
                "hashId": "B802F3E3636AA3506B2F1C5AC12F848B",
                "unixtime": "1473753907",
                "updatetime": "2016-09-13 16:05:07",
                "url": "http://juheimg.oss-cn-hangzhou.aliyuncs.com/joke/201609/13/B802F3E3636AA3506B2F1C5AC12F848B.png"
            },
            {
                "content": "细数一下那些坑爹的产品包装，太坑爹了",
                "hashId": "8814BB8E2F003BCE199DC08C8CC12234",
                "unixtime": "1473753907",
                "updatetime": "2016-09-13 16:05:07",
                "url": "http://juheimg.oss-cn-hangzhou.aliyuncs.com/joke/201609/13/8814BB8E2F003BCE199DC08C8CC12234.png"
            },
            {
                "content": "为日常生活中的实景换上充满戏剧性的一面",
                "hashId": "4DBB42639CB3AA859B54E1B412027D9A",
                "unixtime": "1473753907",
                "updatetime": "2016-09-13 16:05:07",
                "url": "http://juheimg.oss-cn-hangzhou.aliyuncs.com/joke/201609/13/4DBB42639CB3AA859B54E1B412027D9A.png"
            },
            {
                "content": "奇葩的离婚奇俗，离婚要绝食三天！",
                "hashId": "74DC96D679AB326E56A8EBDFD68CD3F9",
                "unixtime": "1473753907",
                "updatetime": "2016-09-13 16:05:07",
                "url": "http://juheimg.oss-cn-hangzhou.aliyuncs.com/joke/201609/13/74DC96D679AB326E56A8EBDFD68CD3F9.png"
            },
            {
                "content": "对胖纸深深的恶意",
                "hashId": "963EC04F41C658DDEA313C409422FD09",
                "unixtime": "1473753907",
                "updatetime": "2016-09-13 16:05:07",
                "url": "http://juheimg.oss-cn-hangzhou.aliyuncs.com/joke/201609/13/963EC04F41C658DDEA313C409422FD09.gif"
            },
            {
                "content": "自带声音的GIF",
                "hashId": "CB93C76E5D5FDBFD3B6D5DD3CB4C4252",
                "unixtime": "1473750306",
                "updatetime": "2016-09-13 15:05:06",
                "url": "http://juheimg.oss-cn-hangzhou.aliyuncs.com/joke/201609/13/CB93C76E5D5FDBFD3B6D5DD3CB4C4252.gif"
            },
            {
                "content": "缺钱的剧组如何拍车戏",
                "hashId": "2AF47ABB09D0543EC876B95C1B6CA4FB",
                "unixtime": "1473750306",
                "updatetime": "2016-09-13 15:05:06",
                "url": "http://juheimg.oss-cn-hangzhou.aliyuncs.com/joke/201609/13/2AF47ABB09D0543EC876B95C1B6CA4FB.gif"
            },
            {
                "content": "激光剑的用法",
                "hashId": "BE01012BD974AFBE6D07437BB14612DD",
                "unixtime": "1473739506",
                "updatetime": "2016-09-13 12:05:06",
                "url": "http://juheimg.oss-cn-hangzhou.aliyuncs.com/joke/201609/13/BE01012BD974AFBE6D07437BB14612DD.jpg"
            },
            {
                "content": "这技能我给满分",
                "hashId": "E39AB1D4FC08BA53EE02CE55C9F4C10E",
                "unixtime": "1473676509",
                "updatetime": "2016-09-12 18:35:09",
                "url": "http://juheimg.oss-cn-hangzhou.aliyuncs.com/joke/201609/12/E39AB1D4FC08BA53EE02CE55C9F4C10E.jpg"
            },
            {
                "content": "打算请室友吃饭，结果...",
                "hashId": "64C95FB80D7B134986D24D695EE1FD69",
                "unixtime": "1473676509",
                "updatetime": "2016-09-12 18:35:09",
                "url": "http://juheimg.oss-cn-hangzhou.aliyuncs.com/joke/201609/12/64C95FB80D7B134986D24D695EE1FD69.jpg"
            },
            {
                "content": "伤不起呀",
                "hashId": "19669914A762BB33D770A11184853BE7",
                "unixtime": "1473676509",
                "updatetime": "2016-09-12 18:35:09",
                "url": "http://juheimg.oss-cn-hangzhou.aliyuncs.com/joke/201609/12/19669914A762BB33D770A11184853BE7.jpg"
            },
            {
                "content": "简直脑洞大开呀",
                "hashId": "2514414A6678A5671FD65B875B6FE48D",
                "unixtime": "1473676509",
                "updatetime": "2016-09-12 18:35:09",
                "url": "http://juheimg.oss-cn-hangzhou.aliyuncs.com/joke/201609/12/2514414A6678A5671FD65B875B6FE48D.jpg"
            },
            {
                "content": "美女，咱们不约",
                "hashId": "4307584616BE53A8EB8896627301669E",
                "unixtime": "1473676509",
                "updatetime": "2016-09-12 18:35:09",
                "url": "http://juheimg.oss-cn-hangzhou.aliyuncs.com/joke/201609/12/4307584616BE53A8EB8896627301669E.jpg"
            }
        ]
    },
    "error_code": "0"
}