{
    "reason": "Success",
    "result": {
        "data": [
            {
                "content": "学生妹放学兼职",
                "hashId": "8080E97C72EB27EE814216B970DB5F2A",
                "unixtime": "1472538959",
                "updatetime": "2016-08-30 14:35:59",
                "url": "http://juheimg.oss-cn-hangzhou.aliyuncs.com/joke/201608/30/8080E97C72EB27EE814216B970DB5F2A.gif"
            },
            {
                "content": "赶紧起来啊别人会误会的",
                "hashId": "AB5E5425AF405B5966C6E25C9EE66C3D",
                "unixtime": "1472538959",
                "updatetime": "2016-08-30 14:35:59",
                "url": "http://juheimg.oss-cn-hangzhou.aliyuncs.com/joke/201608/30/AB5E5425AF405B5966C6E25C9EE66C3D.gif"
            },
            {
                "content": "今晚你就是我的了",
                "hashId": "F35ECA3C78DA426217232F9E8913D687",
                "unixtime": "1472538959",
                "updatetime": "2016-08-30 14:35:59",
                "url": "http://juheimg.oss-cn-hangzhou.aliyuncs.com/joke/201608/30/F35ECA3C78DA426217232F9E8913D687.gif"
            },
            {
                "content": "老板我能不能辞职啊，我找到一份好工作。。。",
                "hashId": "92EA3183E45DD7B5467ABB6C20CA3CB2",
                "unixtime": "1472538959",
                "updatetime": "2016-08-30 14:35:59",
                "url": "http://juheimg.oss-cn-hangzhou.aliyuncs.com/joke/201608/30/92EA3183E45DD7B5467ABB6C20CA3CB2.jpg"
            },
            {
                "content": "屌丝的品味果然与众不同",
                "hashId": "9187A53AFDC0A615097210D53E3802C6",
                "unixtime": "1472538887",
                "updatetime": "2016-08-30 14:34:47",
                "url": "http://juheimg.oss-cn-hangzhou.aliyuncs.com/joke/201608/30/9187A53AFDC0A615097210D53E3802C6.jpg"
            },
            {
                "content": "你能不能好好跟我说话",
                "hashId": "B7CC052F842D3E5676107B0EB3E6E3D7",
                "unixtime": "1472538887",
                "updatetime": "2016-08-30 14:34:47",
                "url": "http://juheimg.oss-cn-hangzhou.aliyuncs.com/joke/201608/30/B7CC052F842D3E5676107B0EB3E6E3D7.jpg"
            },
            {
                "content": "谁特么想出来的",
                "hashId": "EEB26D80B12C70C51ADC02F268FEBF75",
                "unixtime": "1472538887",
                "updatetime": "2016-08-30 14:34:47",
                "url": "http://juheimg.oss-cn-hangzhou.aliyuncs.com/joke/201608/30/EEB26D80B12C70C51ADC02F268FEBF75.jpg"
            },
            {
                "content": "熊孩子在想啥",
                "hashId": "4DFC97D9F336B52FB12D46434C367911",
                "unixtime": "1472538887",
                "updatetime": "2016-08-30 14:34:47",
                "url": "http://juheimg.oss-cn-hangzhou.aliyuncs.com/joke/201608/30/4DFC97D9F336B52FB12D46434C367911.jpg"
            },
            {
                "content": "别惹我动手啊",
                "hashId": "80A9822E0EE9F35CDE19A62E93831BAA",
                "unixtime": "1472538887",
                "updatetime": "2016-08-30 14:34:47",
                "url": "http://juheimg.oss-cn-hangzhou.aliyuncs.com/joke/201608/30/80A9822E0EE9F35CDE19A62E93831BAA.jpg"
            },
            {
                "content": "大步向前走 千万别回头！",
                "hashId": "58C9E9832A741889F8B4BB9CD123F5B4",
                "unixtime": "1472538885",
                "updatetime": "2016-08-30 14:34:45",
                "url": "http://juheimg.oss-cn-hangzhou.aliyuncs.com/joke/201608/30/58C9E9832A741889F8B4BB9CD123F5B4.gif"
            },
            {
                "content": "别人的VS我的",
                "hashId": "D8764FDFD47E313CCC5F7C5EDAEE4CCE",
                "unixtime": "1472538885",
                "updatetime": "2016-08-30 14:34:45",
                "url": "http://juheimg.oss-cn-hangzhou.aliyuncs.com/joke/201608/30/D8764FDFD47E313CCC5F7C5EDAEE4CCE.gif"
            },
            {
                "content": "据说高智商的人看 1 遍就懂了，你看了几遍？",
                "hashId": "DF7CDE544E2F43B3CB5FEAABA31C481B",
                "unixtime": "1472538885",
                "updatetime": "2016-08-30 14:34:45",
                "url": "http://juheimg.oss-cn-hangzhou.aliyuncs.com/joke/201608/30/DF7CDE544E2F43B3CB5FEAABA31C481B.gif"
            },
            {
                "content": "活得不如一只虾努力，难怪我没有六块腹肌",
                "hashId": "DFBB7AE4C03DF6DB7F18BD4960BA5782",
                "unixtime": "1472538885",
                "updatetime": "2016-08-30 14:34:45",
                "url": "http://juheimg.oss-cn-hangzhou.aliyuncs.com/joke/201608/30/DFBB7AE4C03DF6DB7F18BD4960BA5782.gif"
            },
            {
                "content": "穿这种裙子的妹子出门的时候要小心一点身边的人。。。",
                "hashId": "E4E9DFBCC57F3702FE13820A04475B13",
                "unixtime": "1472538885",
                "updatetime": "2016-08-30 14:34:45",
                "url": "http://juheimg.oss-cn-hangzhou.aliyuncs.com/joke/201608/30/E4E9DFBCC57F3702FE13820A04475B13.gif"
            },
            {
                "content": "的多",
                "hashId": "EBDAB5B5E2779BCAE63DE2C339A792D4",
                "unixtime": "1472538885",
                "updatetime": "2016-08-30 14:34:45",
                "url": "http://juheimg.oss-cn-hangzhou.aliyuncs.com/joke/201608/30/EBDAB5B5E2779BCAE63DE2C339A792D4.gif"
            },
            {
                "content": "猫了个咪",
                "hashId": "F6D59892CCA12CE0ACDB66EF2DE3123E",
                "unixtime": "1472538885",
                "updatetime": "2016-08-30 14:34:45",
                "url": "http://juheimg.oss-cn-hangzhou.aliyuncs.com/joke/201608/30/F6D59892CCA12CE0ACDB66EF2DE3123E.gif"
            },
            {
                "content": "朋友一生一起走，那些日子不再有",
                "hashId": "140D89E1AAA25DC0C76950E189D3A2F8",
                "unixtime": "1472538885",
                "updatetime": "2016-08-30 14:34:45",
                "url": "http://juheimg.oss-cn-hangzhou.aliyuncs.com/joke/201608/30/140D89E1AAA25DC0C76950E189D3A2F8.gif"
            },
            {
                "content": "人生最美好的爱情应该就是这样吧",
                "hashId": "51AC288F3B48B649803B9BC6E2414E17",
                "unixtime": "1472538885",
                "updatetime": "2016-08-30 14:34:45",
                "url": "http://juheimg.oss-cn-hangzhou.aliyuncs.com/joke/201608/30/51AC288F3B48B649803B9BC6E2414E17.gif"
            },
            {
                "content": "原来呼啦圈还可以这样玩",
                "hashId": "373B7B8FF4F6C29156F9AE256F03C012",
                "unixtime": "1472538885",
                "updatetime": "2016-08-30 14:34:45",
                "url": "http://juheimg.oss-cn-hangzhou.aliyuncs.com/joke/201608/30/373B7B8FF4F6C29156F9AE256F03C012.gif"
            },
            {
                "content": "老司机倒车请注意！",
                "hashId": "7F47320DB6CE94ABF074E43FAD1DDADE",
                "unixtime": "1472538885",
                "updatetime": "2016-08-30 14:34:45",
                "url": "http://juheimg.oss-cn-hangzhou.aliyuncs.com/joke/201608/30/7F47320DB6CE94ABF074E43FAD1DDADE.gif"
            }
        ]
    },
    "error_code": "0"
}