{
    "reason": "Success",
    "result": {
        "data": [
            {
                "content": "早上幼儿园里，老师准备跟小朋友做游戏：“小盆友们我们玩老鹰抓小鸡好不好？” 紧接着一小姑娘站了出来哭着说：“老师我没有小鸡。”",
                "hashId": "18669228401119188d17bf872263c843",
                "unixtime": "1517237700",
                "updatetime": "2018-01-29 22:55:00"
            },
            {
                "content": "高考快讯微博发过一条博文：高考后你要做的第一件事是什么？ 考生神回复：取消对你的关注……",
                "hashId": "20203658f04e79915d36e4de09d86482",
                "unixtime": "1517237700",
                "updatetime": "2018-01-29 22:55:00"
            },
            {
                "content": "结婚半年了，与哥们出去喝酒。酒过三巡，他咬了咬下唇：“我俩也这么多年了，你婚后我一直想问：你到底有没有爱过...”没等说完，我抬指封住了他的唇：“无需多说，我知道你要问什么，当年我也是身不由己。好吧，我爱过。”他缓缓移开我的手，双眸凝视：“去你妹的~我问你到底有没有挨过你老婆打...”",
                "hashId": "8b62791fe31e0dce4fd76b432c4af7af",
                "unixtime": "1517237700",
                "updatetime": "2018-01-29 22:55:00"
            },
            {
                "content": "几个青年讨论懒到什么地步。 A说：“我的内裤正面穿了穿反面。” B不屑道：“我正面反面前面后面都穿。” 讨论进入到白热话阶段，C插进来说道：“根据数学定理推断，内裤实则为等边三角形，可以旋转着穿。”",
                "hashId": "91ed4cd9c40e9d7620db09032a0ec49f",
                "unixtime": "1517237700",
                "updatetime": "2018-01-29 22:55:00"
            },
            {
                "content": "女1：哇，你的包包好漂亮啊？应该很贵吧？你老公怎么舍得给你买的？ 女2：很贵的。为了买这个包，我嘴皮子都磨破了…… 女1：你都说了什么啊？ 女2：我没工夫说话啊……",
                "hashId": "46cdad54106f6e955c2e2c04e42ad58e",
                "unixtime": "1517237700",
                "updatetime": "2018-01-29 22:55:00"
            },
            {
                "content": "楼上的妹子来我家借用卫生间，进去好长时间没动静，我担心的问：妹子，没事吧？她弱弱的回答:不好意思，突然来了那个，你帮我去买一下好吗？我买来卫生巾从门缝底下塞进去，妹子终于出来了，谢谢了，今天是没法报答你了，过几天好吗？我晕，这话我该怎么理解。",
                "hashId": "9ebb4d62a5e00604b3fd0fa917cf174d",
                "unixtime": "1517237700",
                "updatetime": "2018-01-29 22:55:00"
            },
            {
                "content": "“呀，你这指甲做得好漂亮，都没见过这种颜色！” “是么？” “红里透着黑，黑里夹着紫，紫里又有点蓝，在哪家美甲店做的？” “你刚才关车门夹的。”",
                "hashId": "447d67c887d5fbabc68ba2108a3ea0b1",
                "unixtime": "1517237700",
                "updatetime": "2018-01-29 22:55:00"
            },
            {
                "content": "相亲时，我和对方简单地介绍了一下自己，我：“我不缺钱，但我喜欢坦诚的女人。你呢？” 女：“我愿意嫁你这个丑逼。”",
                "hashId": "c49d0b8951d886dde7f7d9762f7de5d9",
                "unixtime": "1517237700",
                "updatetime": "2018-01-29 22:55:00"
            },
            {
                "content": "下雪了，路上垫了厚厚的一层，大巴车司机仗着自己车技娴熟，依旧保持着高速飞奔状态。坐我旁边的是个美女，她紧紧的咬着嘴唇，小脸煞白，我看她很难受的样子就问她：怎么了？她回过神，强笑了下：没事，这车速，这路况，我有点害怕，我一害怕就特别紧张，一紧张就想抓点什么。我如释重负：噢，原来是这样啊，不要紧的，司机心里有数，不会有事的。你现在可以把手拿开了吗？我感觉我蛋蛋快要捏碎了。",
                "hashId": "3dc7b426821e827b3b5981093666aab3",
                "unixtime": "1517237700",
                "updatetime": "2018-01-29 22:55:00"
            },
            {
                "content": "“如果我说你是我第一个女人，你信吗？” “信!” “为什么？” “解个胸罩你都快墨迹二十分钟了，我有什么理由不信...”",
                "hashId": "94533188664d1ec978957031b6e067b1",
                "unixtime": "1517237700",
                "updatetime": "2018-01-29 22:55:00"
            },
            {
                "content": "我一个女同事兼职做保险，她刚拿驾照不久，开着新车，顺路送我回家。她一开车就跟我叭叭保 险的重要性，我无动于衷。我上她的车十分钟左右，就改变了主意，决定跟她买一份保 险...她三次变道不打转向灯不看后视镜，用她的车别大卡，这让我感到人生无常.......",
                "hashId": "164741cbd42c962870bc932d9c990e9e",
                "unixtime": "1517237700",
                "updatetime": "2018-01-29 22:55:00"
            },
            {
                "content": "以后你结婚了，如果新郎不是我，我就搬到你家隔壁去住，对你孩子比对亲生的还好，直到让你老公怀疑人生……",
                "hashId": "9e9aff5601a5347e0eca2c103cca3d1f",
                "unixtime": "1517237700",
                "updatetime": "2018-01-29 22:55:00"
            },
            {
                "content": "今天女同事全部逛商场去了，办公室全部剩下男同胞了。老板进门看了看说：“怎么光剩下插头了，插座都哪去了？”",
                "hashId": "4913f240f5328b21cda46837ccdb4484",
                "unixtime": "1517237700",
                "updatetime": "2018-01-29 22:55:00"
            },
            {
                "content": "俩乞丐在一起聊天：甲：贫穷真是限制了我的想象！乙：咋啦？甲：刚才有个人居然一次性打赏我三张卡！乙：天啦！什么卡？甲：卖发票、刻公章、拉皮条！乙：。。。。。",
                "hashId": "7a3f814f2d664e4ff3461c1e9ea19b82",
                "unixtime": "1517237700",
                "updatetime": "2018-01-29 22:55:00"
            },
            {
                "content": "学霸算个屁，跟我一比，简直不值一提首先，学霸的文采没我好，他写的作文只有老师欣赏，而我写的情书，成为全班传抄的典范。其次，学霸的名气没我大，他只是在学校知名，而我，只要一提张小明，大家都会说:“认识，认识，大冬天裸奔的，谁不认识”再次，学霸的人脉没有我广，他就认识几个老师和成绩好的同学，而我，全校全区的学渣都和我有来往。怎么样，还是我厉害吧！",
                "hashId": "af4ea24a8121a6e80772dd4d76d45361",
                "unixtime": "1517237700",
                "updatetime": "2018-01-29 22:55:00"
            },
            {
                "content": "昨晚，我听到爸妈房间在争吵老妈:“都怪你妈，如果不是你妈咱儿子能成这样吗？”老爸:“我妈怎么了？”老妈:“生儿子之前，你妈买小礼物，说如果是孙子就送玩具汽车，如果是孙女就送洋娃娃，结果你妈既买了小汽车又买了洋娃娃”老爸:“我妈不是想生个双胞胎吗”老妈:“狗屁，现在咱儿子这么娘，就得怪你妈”",
                "hashId": "5f053d0428c1ef3770b41809b36d0636",
                "unixtime": "1517237700",
                "updatetime": "2018-01-29 22:55:00"
            },
            {
                "content": "男朋友非要拉着我吃火锅，我说怕吃辣，男朋友说微辣，不要紧的。火锅上来，我吃了一口，辣的我流眼泪，我骂男朋友:“你个便宜，你不说是微辣吗”男朋友:“咱没见面以前，你不也在网上对我说自己是微胖吗”我:“~”",
                "hashId": "f2706a42d0244fde029049ed9c37f5d0",
                "unixtime": "1517237700",
                "updatetime": "2018-01-29 22:55:00"
            },
            {
                "content": "老婆问我:“老公，你知道楼下小王吗，他老婆是我闺蜜，怀疑他藏私房钱，你能不能告诉我，他私房钱藏哪里？”我暗自高兴，早就看这小子不顺眼了，这次要大仇得报，于是我说道:“老婆，男人藏私房钱，第一在鞋底，第二在旧衣，第三在床头，第四在纸篓”，老婆点头，飞快的把我说的这四个地方翻了个底朝天，老婆拿着搜刮来的800块，恶狠狠的骂道:“马勒戈壁的，小王给我说你藏私房钱我还不信，你特码找死是不是！”",
                "hashId": "79db3b98220810ad82d2b75a68d3c764",
                "unixtime": "1517237700",
                "updatetime": "2018-01-29 22:55:00"
            },
            {
                "content": "今天去相亲，相互觉得很满意，决定交往下去，她突然说道:“既然是情侣了，就得真诚，其实……我化妆了”，说完，跑进洗手间，卸掉了妆，吓的我心惊肉跳。我也说道:“那我也不瞒你了，其实，我脚很臭”，说着我脱掉了鞋子，臭的她差点晕了过去她摆了摆手:“没事，我有鼻炎”我又说道:“其实，我这宝马车钥匙是个模型”她笑了笑:“可以接受，其实，我以前谈过5个男朋友”我:“五个不多，我也可以接受”她又说:“真的吗，你果然和别人不一样，别人都说是我把他们5个克死的”我:“我靠，都死了？”",
                "hashId": "35e197277e0797b5b05d8145df00217f",
                "unixtime": "1517237700",
                "updatetime": "2018-01-29 22:55:00"
            },
            {
                "content": "昨晚路过车站，有个漂亮的少妇小声问我:“哥，要鸡不？”我兴奋:“要，好看吗？多少钱？”少妇:“哥，你放心，绝对好看，200”我:“给我便宜点”少妇:“好，150，先交钱”我给了她150块，然后问:“去哪里交易？”少妇大声喊:“老公，这位兄弟要鸡仔一只”就在这时，一个彪形大汉手里捧着一只小鸡仔出来，大声吆喝:“我最讨厌言而无信的人，货已售概不退换！”我:“……”",
                "hashId": "a66771c773286b14f8398231709341a2",
                "unixtime": "1517237700",
                "updatetime": "2018-01-29 22:55:00"
            }
        ]
    },
    "error_code": "0"
}